tools/__init__.py
tools/sarscov2vec.py
sarscov2vec-1.0.0.dist-info/LICENSE
sarscov2vec-1.0.0.dist-info/METADATA
sarscov2vec-1.0.0.dist-info/WHEEL
sarscov2vec-1.0.0.dist-info/top_level.txt
sarscov2vec-1.0.0.dist-info/RECORD
