Metadata-Version: 2.1
Name: sarscov2vec
Version: 1.0.0
Summary: sarscov2vec is an application of continuous vector space representation on novel species of coronaviruses genomes as the methodology of genome feature extraction step, to distinguish the most common different SARS-CoV-2 variants by supervised machine learning model.
Home-page: https://github.com/ptynecki/sarscov2vec
Download-URL: https://github.com/ptynecki/sarscov2vec/archive/v1.0.0.tar.gz
Author: Piotr Tynecki & Marcin Lubocki
Author-email: p.tynecki@doktoranci.pb.edu.pl
License: MIT
Keywords: SARS-CoV-2,GISAID,COVID-19,continuous embedding,genome sequence embedding,virus bioinformatics,sequence analysis
Platform: UNKNOWN
Classifier: Development Status :: 3 - Alpha
Classifier: License :: OSI Approved :: MIT License
Classifier: Programming Language :: Python :: 3.8
Requires-Python: >=3.8
License-File: LICENSE
Requires-Dist: fasttext (==0.9.2)
Requires-Dist: scikit-learn (==1.0.2)
Requires-Dist: pandas (==1.4.2)
Requires-Dist: joblib (==1.1.0)
Requires-Dist: biopython (==1.79)
